{
  "signal": [
    {
      "name": "MODEL STEP",
      "wave": "==",
      "data": [
        "0",
        "1"
      ]
    },
    [
      "AW",
      {
        "name": "CanonicalEvent",
        "wave": "=x",
        "data": [
          "12@0x308:1x4I"
        ]
      }
    ],
    [
      "W",
      {
        "name": "CanonicalEvent",
        "wave": "x=",
        "data": [
          "D0x0/Sf/L0"
        ]
      }
    ],
    {
      "name": "COMMITTED",
      "wave": "10"
    },
    {
      "name": "MODEL FAULT",
      "wave": "x1"
    }
  ],
  "head": {
    "text": "The final required W transfer asserts WLAST / 最后一拍必需的 W 传输必须置 WLAST"
  },
  "foot": {
    "text": "1 column = 1 CanonicalEvent · MODEL ORDER ONLY · NOT PINS/CYCLES/RTL / 非引脚时序"
  },
  "config": {
    "hscale": 9
  }
}
